python_jsonapi/__init__.py
python_jsonapi/__main__.py
python_jsonapi/core/__init__.py
python_jsonapi/core/types/__init__.py
python_jsonapi/core/types/error.py
python_jsonapi/core/types/links.py
python_jsonapi/core/types/meta.py
python_jsonapi/core/types/relationships.py
python_jsonapi/core/types/resource.py
python_jsonapi/core/types/resource_identifier.py
python_jsonapi/py.typed
python_jsonapi-0.0.1.dist-info/entry_points.txt
python_jsonapi-0.0.1.dist-info/LICENSE.rst
python_jsonapi-0.0.1.dist-info/WHEEL
python_jsonapi-0.0.1.dist-info/METADATA
python_jsonapi-0.0.1.dist-info/RECORD
