Metadata-Version: 2.1
Name: python-jsonapi
Version: 0.0.1
Summary: Python JSON:API
Home-page: https://github.com/jeffsawatzky/python-jsonapi
License: MIT
Author: Jeff Sawatzky
Author-email: jeff.sawatzky@me.com
Requires-Python: >=3.8.0,<4.0.0
Classifier: License :: OSI Approved :: MIT License
Classifier: Programming Language :: Python :: 3
Classifier: Programming Language :: Python :: 3.8
Requires-Dist: click (>=7.0,<8.0)
Requires-Dist: uri (>=2.0.1,<3.0.0)
Project-URL: Changelog, https://github.com/jeffsawatzky/python-jsonapi/releases
Project-URL: Documentation, https://python-jsonapi.readthedocs.io
Project-URL: Repository, https://github.com/jeffsawatzky/python-jsonapi
